LICENSE
MANIFEST.in
README.rst
buildout.cfg
develop.cfg
requirements.txt
setup.py
version.txt
bob/__init__.py
bob.db.cohface.egg-info/PKG-INFO
bob.db.cohface.egg-info/SOURCES.txt
bob.db.cohface.egg-info/dependency_links.txt
bob.db.cohface.egg-info/entry_points.txt
bob.db.cohface.egg-info/not-zip-safe
bob.db.cohface.egg-info/requires.txt
bob.db.cohface.egg-info/top_level.txt
bob/db/__init__.py
bob/db/cohface/__init__.py
bob/db/cohface/detect_peaks.py
bob/db/cohface/driver.py
bob/db/cohface/files.txt
bob/db/cohface/models.py
bob/db/cohface/test.py
bob/db/cohface/utils.py